aiostalk.py
aiostalk-1.3.1.dist-info/licenses/LICENSE
aiostalk-1.3.1.dist-info/METADATA
aiostalk-1.3.1.dist-info/WHEEL
aiostalk-1.3.1.dist-info/top_level.txt
aiostalk-1.3.1.dist-info/RECORD
